{
	"uuid": "line_a",

	"components":
	{
		"transform":
		[
			{
				"name": "position",
				"float32": [0, 3, 0]
			},

			{
				"name": "rotation",
				"float32": [0, 0, 0, 1]
			},

			{
				"name": "scale",
				"float32": [1, 1, 1]
			},

			{
				"name": "parent",
				"uuid": ""
			},

			{
				"name": "first child",
				"uuid": ""
			},

			{
				"name": "next sibling",
				"uuid": ""
			},

			{
				"name": "dirty",
				"bool": true
			},

			{
				"name": "global position",
				"float32": [0.0, 0.0, 0.0]
			},

			{
				"name": "global rotation",
				"float32": [0.0, 0.0, 0.0, 1.0]
			},

			{
				"name": "global scale",
				"float32": [1.0, 1.0, 1.0]
			},

			{
				"name": "last global position",
				"float32": [0.0, 0.0, 0.0]
			},

			{
				"name": "last global rotation",
				"float32": [0.0, 0.0, 0.0, 1.0]
			},

			{
				"name": "last global scale",
				"float32": [1.0, 1.0, 1.0]
			}
		],

		"debug_primitive":
		[
			{
				"name": "visible",
				"bool": true
			},

			{
				"name": "debug primitive type",
				"int32": 1
			},

			{
				"name": "size",
				"float32": 1.0
			},

			{
				"name": "color",
				"float32": [0.0, 1.0, 0.0]
			},

			{
				"name": "endpoint",
				"uuid": "line_b"
			},

			{
				"name": "endpoint color",
				"float32": [0.0, 0.0, 1.0]
			}
		]
	}
}
