{
  "uuid": ">mZ$D=sta9_*ly7'y_`ax#Hfhrne?UqZ@IacLSJb0IM'UQ';79/#utjiW/<FfRl",
  "components": {
    "transform": [
      {
        "name": "position",
        "float32": [
          0,
          0,
          0
        ]
      },
      {
        "name": "rotation",
        "float32": [
          0,
          0,
          0,
          1
        ]
      },
      {
        "name": "scale",
        "float32": [
          1,
          1,
          1
        ]
      },
      {
        "name": "parent",
        "uuid": ""
      },
      {
        "name": "firstChild",
        "uuid": ""
      },
      {
        "name": "nextSibling",
        "uuid": ""
      },
      {
        "name": "dirty",
        "bool": true
      },
      {
        "name": "globalPosition",
        "float32": [
          0,
          0,
          0
        ]
      },
      {
        "name": "globalRotation",
        "float32": [
          0,
          0,
          0,
          1
        ]
      },
      {
        "name": "globalScale",
        "float32": [
          1,
          1,
          1
        ]
      },
      {
        "name": "lastGlobalPosition",
        "float32": [
          0,
          0,
          0
        ]
      },
      {
        "name": "lastGlobalRotation",
        "float32": [
          0,
          0,
          0,
          1
        ]
      },
      {
        "name": "lastGlobalScale",
        "float32": [
          1,
          1,
          1
        ]
      }
    ],
    "model": [
      {
        "name": "filename",
        "char(1024)": "box"
      },
      {
        "name": "visible",
        "bool": true
      }
    ]
  }
}
