{
	"uuid": "OrBdtA9;b.d4`q7jjg7cDpCCOH'GRs.'dMaVdwgL#Q`IiI9VUrxL;9x`>>0/I-p",

	"components":
	{
		"transform":
		[
			{
				"name": "position",
				"float32": [0, 0.018368953838944435, 0]
			},

			{
				"name": "rotation",
				"float32": [0, 0, 0, 1]
			},

			{
				"name": "scale",
				"float32": [1, 1, 1]
			},

			{
				"name": "parent",
				"uuid": "GbG_Gten)@A7LB>4h^SJfXD+'@hDwHg<(4xL&8-yWAKnTT0%-sGs_dayY(fr-oh"
			},

			{
				"name": "first child",
				"uuid": ""
			},

			{
				"name": "next sibling",
				"uuid": ""
			},

			{
				"name": "dirty",
				"bool": true
			},

			{
				"name": "global position",
				"float32": [0, 0, 0]
			},

			{
				"name": "global rotation",
				"float32": [0, 0, 0, 1]
			},

			{
				"name": "global scale",
				"float32": [1, 1, 1]
			},

			{
				"name": "last global position",
				"float32": [0, 0, 0]
			},

			{
				"name": "last global rotation",
				"float32": [0, 0, 0, 1]
			},

			{
				"name": "last global scale",
				"float32": [1, 1, 1]
			}
		],

		"joint":
		[
			{
				"name": "name",
				"char(64)": "aug_lied_O_R_end"
			}
		]
	}
}
