{
	"uuid": "rXaeu+>sKFNGp3c=C9ijgFtJ-N.wTcg3KR&Kenl2:1(KqBk(*SlEEFdGqoEKP*S",

	"components":
	{
		"transform":
		[
			{
				"name": "position",
				"float32":
				[
					-3.14321368932724e-09,
					0.098762504756450653,
					-1.2543750926852226e-08
				]
			},

			{
				"name": "rotation",
				"float32":
				[
					-0.70860272645950317,
					-0.038430206477642059,
					-0.01185584906488657,
					0.70446068048477173
				]
			},

			{
				"name": "scale",
				"float32":
				[
					0.99999988079071045,
					1.0000001192092896,
					1.0000001192092896
				]
			},

			{
				"name": "parent",
				"uuid": "9ECN1xgCXd*ZVUL6LuE+*B42e@R0)Z^7%'Z,u?DS)K3uTgGO2OOJYV-v/:tfm)`"
			},

			{
				"name": "first child",
				"uuid": "xZNBE;,LR:I#)ac/h<p+W<l$3aFT7F%.&IE@aNb91:co#gU5VigOjp./J;RD>Mj"
			},

			{
				"name": "next sibling",
				"uuid": ""
			},

			{
				"name": "dirty",
				"bool": true
			},

			{
				"name": "global position",
				"float32": [0, 0, 0]
			},

			{
				"name": "global rotation",
				"float32": [0, 0, 0, 1]
			},

			{
				"name": "global scale",
				"float32": [1, 1, 1]
			},

			{
				"name": "last global position",
				"float32": [0, 0, 0]
			},

			{
				"name": "last global rotation",
				"float32": [0, 0, 0, 1]
			},

			{
				"name": "last global scale",
				"float32": [1, 1, 1]
			}
		],

		"joint":
		[
			{
				"name": "name",
				"char(64)": "Pfote2_L"
			}
		]
	}
}
